aiomtec2mqtt/__init__.py
aiomtec2mqtt/async_coordinator.py
aiomtec2mqtt/async_modbus_client.py
aiomtec2mqtt/async_mqtt_client.py
aiomtec2mqtt/config-template.yaml
aiomtec2mqtt/config.py
aiomtec2mqtt/const.py
aiomtec2mqtt/container.py
aiomtec2mqtt/exceptions.py
aiomtec2mqtt/formula_evaluator.py
aiomtec2mqtt/hass_int.py
aiomtec2mqtt/health.py
aiomtec2mqtt/install.py
aiomtec2mqtt/prometheus_metrics.py
aiomtec2mqtt/protocols.py
aiomtec2mqtt/py.typed
aiomtec2mqtt/register_models.py
aiomtec2mqtt/register_processors.py
aiomtec2mqtt/registers.yaml
aiomtec2mqtt/resilience.py
aiomtec2mqtt/shutdown.py
aiomtec2mqtt/structured_logging.py
aiomtec2mqtt/sync_coordinator_wrapper.py
aiomtec2mqtt/testing.py
aiomtec2mqtt/util/__init__.py
aiomtec2mqtt/util/mtec_util.py
aiomtec2mqtt-1.0.6.dist-info/licenses/LICENSE
aiomtec2mqtt-1.0.6.dist-info/METADATA
aiomtec2mqtt-1.0.6.dist-info/WHEEL
aiomtec2mqtt-1.0.6.dist-info/entry_points.txt
aiomtec2mqtt-1.0.6.dist-info/top_level.txt
aiomtec2mqtt-1.0.6.dist-info/RECORD
