Metadata-Version: 2.4
Name: aiomtec2mqtt
Version: 1.0.6
Summary: Read data from a M-TEC Energybutler system and write them to a MQTT broker
Home-page: https://github.com/sukramj/aiomtec2mqtt
Author-email: SukramJ <sukramj@icloud.com>, Christian Rödel <christian@roedel.info>
License: Copyright (c) 2024 Christian Rödel
Project-URL: Source Code, https://github.com/sukramj/aiomtec2mqtt
Project-URL: Bug Reports, https://github.com/sukramj/aiomtec2mqtt/issues
Project-URL: Docs: Dev, https://github.com/sukramj/aiomtec2mqtt
Project-URL: Forum, https://github.com/sukramj/aiomtec2mqtt/discussions
Keywords: home,automation,mtec,mqtt,modbus
Classifier: Development Status :: 4 - Beta
Classifier: Intended Audience :: End Users/Desktop
Classifier: Intended Audience :: Developers
Classifier: License :: OSI Approved :: GNU Library or Lesser General Public License (LGPL)
Classifier: Operating System :: OS Independent
Classifier: Programming Language :: Python :: 3.13
Classifier: Topic :: Home Automation
Requires-Python: >=3.13.0
License-File: LICENSE
Requires-Dist: pyyaml>=6.0.2
Requires-Dist: PyModbus>=3.11.4
Requires-Dist: aiomqtt>=2.5.0
Requires-Dist: pydantic>=2.12.0
Requires-Dist: prometheus-client>=0.21.0
Dynamic: license-file
